{
	"credit": "Made with Blockbench",
	"parent": "lom:item/hats/simplehats/hatparent",
	"texture_size": [32, 32],
	"textures": {
		"0": "lom:item/hats/simplehats/batwinghat"
	},
	"elements": [
		{
			"from": [1.97217, 5.52722, 7],
			"to": [4.97217, 6.52722, 8],
			"rotation": {"angle": 22.5, "axis": "z", "origin": [-1.36091, 6.78782, 7.525]},
			"faces": {
				"north": {"uv": [1, 6.5, 2, 7], "texture": "#0", "tintindex": 0},
				"east": {"uv": [4, 6.5, 4.5, 7], "texture": "#0", "tintindex": 0},
				"south": {"uv": [2, 6.5, 3, 7], "texture": "#0", "tintindex": 0},
				"west": {"uv": [1, 7, 1.5, 7.5], "texture": "#0", "tintindex": 0},
				"up": {"uv": [4, 7, 3, 6.5], "texture": "#0", "tintindex": 0},
				"down": {"uv": [7.5, 4.5, 6.5, 5], "texture": "#0", "tintindex": 0}
			}
		},
		{
			"from": [1.97217, 5.52722, 7],
			"to": [4.97217, 6.52722, 8],
			"rotation": {"angle": 22.5, "axis": "z", "origin": [-1.36091, 6.78782, 7.525]},
			"faces": {
				"north": {"uv": [1, 6.5, 2, 7], "texture": "#0", "tintindex": 0},
				"east": {"uv": [4, 6.5, 4.5, 7], "texture": "#0", "tintindex": 0},
				"south": {"uv": [2, 6.5, 3, 7], "texture": "#0", "tintindex": 0},
				"west": {"uv": [1, 7, 1.5, 7.5], "texture": "#0", "tintindex": 0},
				"up": {"uv": [4, 7, 3, 6.5], "texture": "#0", "tintindex": 0},
				"down": {"uv": [7.5, 4.5, 6.5, 5], "texture": "#0", "tintindex": 0}
			}
		},
		{
			"from": [-3.96044, 7.48792, 7],
			"to": [0.03956, 8.48792, 8],
			"rotation": {"angle": -22.5, "axis": "z", "origin": [-1.36091, 6.78782, 7.525]},
			"faces": {
				"north": {"uv": [4.5, 6, 5, 8], "rotation": 90, "texture": "#0", "tintindex": 0},
				"east": {"uv": [2.5, 7, 2, 7.5], "rotation": 270, "texture": "#0", "tintindex": 0},
				"south": {"uv": [5, 6, 5.5, 8], "rotation": 270, "texture": "#0", "tintindex": 0},
				"west": {"uv": [2, 7.5, 1.5, 7], "rotation": 270, "texture": "#0", "tintindex": 0},
				"up": {"uv": [6, 4.5, 6.5, 6.5], "rotation": 270, "texture": "#0", "tintindex": 0},
				"down": {"uv": [5.5, 6, 6, 8], "rotation": 270, "texture": "#0", "tintindex": 0}
			}
		},
		{
			"from": [-3.31344, -0.20743, 7.275],
			"to": [-2.81344, 8.79257, 7.775],
			"rotation": {"angle": 0, "axis": "y", "origin": [-1.36091, 6.78782, 7.525]},
			"faces": {
				"north": {"uv": [6, 3.5, 10.5, 3.75], "rotation": 90, "texture": "#0", "tintindex": 0},
				"east": {"uv": [10.5, 2, 6, 2.5], "rotation": 270, "texture": "#0", "tintindex": 0},
				"south": {"uv": [6, 4, 10.5, 4.25], "rotation": 270, "texture": "#0", "tintindex": 0},
				"west": {"uv": [10.5, 2, 6, 1.5], "rotation": 270, "texture": "#0", "tintindex": 0},
				"up": {"uv": [6, 7, 6.5, 7.25], "rotation": 270, "texture": "#0", "tintindex": 0},
				"down": {"uv": [6.5, 7, 7, 7.25], "rotation": 270, "texture": "#0", "tintindex": 0}
			}
		},
		{
			"from": [-10.28502, 8.84008, 7],
			"to": [-0.78502, 9.84008, 8],
			"rotation": {"angle": 45, "axis": "z", "origin": [-1.36091, 6.78782, 7.525]},
			"faces": {
				"north": {"uv": [0, 6, 4.5, 6.5], "texture": "#0", "tintindex": 0},
				"east": {"uv": [3.5, 7, 4, 7.5], "texture": "#0", "tintindex": 0},
				"south": {"uv": [6, 0, 10.5, 0.5], "texture": "#0", "tintindex": 0},
				"west": {"uv": [4, 7, 4.5, 7.5], "texture": "#0", "tintindex": 0},
				"up": {"uv": [10.5, 1, 6, 0.5], "texture": "#0", "tintindex": 0},
				"down": {"uv": [10.5, 1, 6, 1.5], "texture": "#0", "tintindex": 0}
			}
		},
		{
			"from": [0.20087, 6.89869, 7],
			"to": [2.20087, 7.89869, 8],
			"rotation": {"angle": 0, "axis": "y", "origin": [-1.36091, 6.78782, 7.525]},
			"faces": {
				"north": {"uv": [6.5, 5, 7.5, 5.5], "texture": "#0", "tintindex": 0},
				"east": {"uv": [2.5, 7, 3, 7.5], "texture": "#0", "tintindex": 0},
				"south": {"uv": [6.5, 5.5, 7.5, 6], "texture": "#0", "tintindex": 0},
				"west": {"uv": [3, 7, 3.5, 7.5], "texture": "#0"},
				"up": {"uv": [7, 7, 6, 6.5], "texture": "#0", "tintindex": 0},
				"down": {"uv": [7.5, 6, 6.5, 6.5], "texture": "#0", "tintindex": 0}
			}
		},
		{
			"from": [-9.82373, 2.80192, 7.5],
			"to": [2.17627, 9.30192, 7.6],
			"rotation": {"angle": 45, "axis": "z", "origin": [-1.36091, 6.78782, 7.525]},
			"faces": {
				"north": {"uv": [0.016, 0.016, 5.984, 3.234], "texture": "#0", "tintindex": 0},
				"east": {"uv": [9.016, 5.016, 9.25, 7.984], "texture": "#0", "tintindex": 0},
				"south": {"uv": [5.984, 0.016, 0.016, 3.234], "texture": "#0", "tintindex": 0},
				"west": {"uv": [10.25, 6.25, 10.484, 9.25], "texture": "#0"},
				"up": {"uv": [8.984, 9.25, 3.016, 9.016], "texture": "#0", "tintindex": 0},
				"down": {"uv": [8.984, 8.516, 3.016, 8.75], "texture": "#0", "tintindex": 0}
			}
		},
		{
			"from": [4.09535, 7.93466, 6.8],
			"to": [5.09535, 14.93466, 7.8],
			"rotation": {"angle": -22.5, "axis": "x", "origin": [4.59535, 9.43466, 7.3]},
			"faces": {
				"north": {"uv": [7.5, 5, 6.5, 4.5], "rotation": 270, "texture": "#0", "tintindex": 0},
				"east": {"uv": [1, 7, 2, 6.5], "rotation": 90, "texture": "#0", "tintindex": 0},
				"south": {"uv": [4, 6.5, 3, 7], "rotation": 270, "texture": "#0", "tintindex": 0},
				"west": {"uv": [2, 7, 3, 6.5], "rotation": 270, "texture": "#0", "tintindex": 0},
				"up": {"uv": [4, 7, 4.5, 6.5], "texture": "#0", "tintindex": 0},
				"down": {"uv": [1, 7.5, 1.5, 7], "rotation": 180, "texture": "#0", "tintindex": 0}
			}
		},
		{
			"from": [11.02783, 5.52722, 7],
			"to": [14.02783, 6.52722, 8],
			"rotation": {"angle": -22.5, "axis": "z", "origin": [17.36091, 6.78782, 7.525]},
			"faces": {
				"north": {"uv": [2, 6.5, 1, 7], "texture": "#0", "tintindex": 0},
				"east": {"uv": [1.5, 7, 1, 7.5], "texture": "#0", "tintindex": 0},
				"south": {"uv": [3, 6.5, 2, 7], "texture": "#0", "tintindex": 0},
				"west": {"uv": [4.5, 6.5, 4, 7], "texture": "#0", "tintindex": 0},
				"up": {"uv": [3, 7, 4, 6.5], "texture": "#0", "tintindex": 0},
				"down": {"uv": [6.5, 4.5, 7.5, 5], "texture": "#0", "tintindex": 0}
			}
		},
		{
			"from": [11.02783, 5.52722, 7],
			"to": [14.02783, 6.52722, 8],
			"rotation": {"angle": -22.5, "axis": "z", "origin": [17.36091, 6.78782, 7.525]},
			"faces": {
				"north": {"uv": [2, 6.5, 1, 7], "texture": "#0", "tintindex": 0},
				"east": {"uv": [1.5, 7, 1, 7.5], "texture": "#0", "tintindex": 0},
				"south": {"uv": [3, 6.5, 2, 7], "texture": "#0", "tintindex": 0},
				"west": {"uv": [4.5, 6.5, 4, 7], "texture": "#0", "tintindex": 0},
				"up": {"uv": [3, 7, 4, 6.5], "texture": "#0", "tintindex": 0},
				"down": {"uv": [6.5, 4.5, 7.5, 5], "texture": "#0", "tintindex": 0}
			}
		},
		{
			"from": [15.96044, 7.48792, 7],
			"to": [19.96044, 8.48792, 8],
			"rotation": {"angle": 22.5, "axis": "z", "origin": [17.36091, 6.78782, 7.525]},
			"faces": {
				"north": {"uv": [4.5, 8, 5, 6], "rotation": 90, "texture": "#0", "tintindex": 0},
				"east": {"uv": [2, 7, 1.5, 7.5], "rotation": 270, "texture": "#0", "tintindex": 0},
				"south": {"uv": [5, 8, 5.5, 6], "rotation": 270, "texture": "#0", "tintindex": 0},
				"west": {"uv": [2.5, 7.5, 2, 7], "rotation": 270, "texture": "#0", "tintindex": 0},
				"up": {"uv": [6, 6.5, 6.5, 4.5], "rotation": 270, "texture": "#0", "tintindex": 0},
				"down": {"uv": [5.5, 8, 6, 6], "rotation": 270, "texture": "#0", "tintindex": 0}
			}
		},
		{
			"from": [18.81344, -0.20743, 7.275],
			"to": [19.31344, 8.79257, 7.775],
			"rotation": {"angle": 0, "axis": "y", "origin": [17.36091, 6.78782, 7.525]},
			"faces": {
				"north": {"uv": [6, 3.75, 10.5, 3.5], "rotation": 90, "texture": "#0", "tintindex": 0},
				"east": {"uv": [10.5, 1.5, 6, 2], "rotation": 270, "texture": "#0", "tintindex": 0},
				"south": {"uv": [6, 4.25, 10.5, 4], "rotation": 270, "texture": "#0", "tintindex": 0},
				"west": {"uv": [10.5, 2.5, 6, 2], "rotation": 270, "texture": "#0", "tintindex": 0},
				"up": {"uv": [6, 7.25, 6.5, 7], "rotation": 270, "texture": "#0", "tintindex": 0},
				"down": {"uv": [6.5, 7.25, 7, 7], "rotation": 270, "texture": "#0", "tintindex": 0}
			}
		},
		{
			"from": [16.78502, 8.84008, 7],
			"to": [26.28502, 9.84008, 8],
			"rotation": {"angle": -45, "axis": "z", "origin": [17.36091, 6.78782, 7.525]},
			"faces": {
				"north": {"uv": [4.5, 6, 0, 6.5], "texture": "#0", "tintindex": 0},
				"east": {"uv": [4.5, 7, 4, 7.5], "texture": "#0", "tintindex": 0},
				"south": {"uv": [10.5, 0, 6, 0.5], "texture": "#0", "tintindex": 0},
				"west": {"uv": [4, 7, 3.5, 7.5], "texture": "#0", "tintindex": 0},
				"up": {"uv": [6, 1, 10.5, 0.5], "texture": "#0", "tintindex": 0},
				"down": {"uv": [6, 1, 10.5, 1.5], "texture": "#0", "tintindex": 0}
			}
		},
		{
			"from": [13.79913, 6.89869, 7],
			"to": [15.79913, 7.89869, 8],
			"rotation": {"angle": 0, "axis": "y", "origin": [17.36091, 6.78782, 7.525]},
			"faces": {
				"north": {"uv": [7.5, 5, 6.5, 5.5], "texture": "#0", "tintindex": 0},
				"east": {"uv": [3.5, 7, 3, 7.5], "texture": "#0"},
				"south": {"uv": [7.5, 5.5, 6.5, 6], "texture": "#0", "tintindex": 0},
				"west": {"uv": [3, 7, 2.5, 7.5], "texture": "#0", "tintindex": 0},
				"up": {"uv": [6, 7, 7, 6.5], "texture": "#0", "tintindex": 0},
				"down": {"uv": [6.5, 6, 7.5, 6.5], "texture": "#0", "tintindex": 0}
			}
		},
		{
			"from": [13.82373, 2.80192, 7.5],
			"to": [25.82373, 9.30192, 7.6],
			"rotation": {"angle": -45, "axis": "z", "origin": [17.36091, 6.78782, 7.525]},
			"faces": {
				"north": {"uv": [5.984, 0.016, 0.016, 3.234], "texture": "#0", "tintindex": 0},
				"east": {"uv": [10.484, 6.25, 10.25, 9.25], "texture": "#0"},
				"south": {"uv": [0.016, 0.016, 5.984, 3.234], "texture": "#0", "tintindex": 0},
				"west": {"uv": [9.25, 5.016, 9.016, 7.984], "texture": "#0", "tintindex": 0},
				"up": {"uv": [3.016, 9.25, 8.984, 9.016], "texture": "#0", "tintindex": 0},
				"down": {"uv": [3.016, 8.516, 8.984, 8.75], "texture": "#0", "tintindex": 0}
			}
		},
		{
			"from": [10.90465, 7.93466, 6.8],
			"to": [11.90465, 14.93466, 7.8],
			"rotation": {"angle": -22.5, "axis": "x", "origin": [11.40465, 9.43466, 7.3]},
			"faces": {
				"north": {"uv": [7.5, 4.5, 6.5, 5], "rotation": 270, "texture": "#0", "tintindex": 0},
				"east": {"uv": [2, 6.5, 3, 7], "rotation": 270, "texture": "#0", "tintindex": 0},
				"south": {"uv": [4, 7, 3, 6.5], "rotation": 270, "texture": "#0", "tintindex": 0},
				"west": {"uv": [1, 6.5, 2, 7], "rotation": 90, "texture": "#0", "tintindex": 0},
				"up": {"uv": [4.5, 7, 4, 6.5], "texture": "#0", "tintindex": 0},
				"down": {"uv": [1.5, 7.5, 1, 7], "rotation": 180, "texture": "#0", "tintindex": 0}
			}
		}
	],
	"display": {
		"thirdperson_righthand": {
			"rotation": [70, 0, 0],
			"translation": [-5.5, -6.25, 2.75]
		},
		"thirdperson_lefthand": {
			"rotation": [70, 0, 0],
			"translation": [-5.5, -6.25, 2.75]
		},
		"firstperson_righthand": {
			"rotation": [0, 0, -67.25],
			"translation": [7.25, -2, 0],
			"scale": [0.5, 0.5, 0.5]
		},
		"firstperson_lefthand": {
			"rotation": [0, 0, -67.25],
			"translation": [7.25, -2, 0],
			"scale": [0.5, 0.5, 0.5]
		},
		"ground": {
			"translation": [0, 4.25, 0]
		},
		"gui": {
			"rotation": [35, -135, 0],
			"translation": [0, -2, 0],
			"scale": [0.5, 0.5, 0.5]
		},
		"head": {
			"rotation": [-35, 0, 0]
		},
		"fixed": {
			"rotation": [0, 180, 0],
			"translation": [0, -3.25, -3.5],
			"scale": [2.5, 2.5, 2.5]
		}
	},
	"groups": [
		{
			"name": "group",
			"origin": [-6, 10, 0],
			"color": 0,
			"children": [0, 1, 2, 3, 4, 5, 6]
		},
		7,
		{
			"name": "group",
			"origin": [-6, 10, 0],
			"color": 0,
			"children": [8, 9, 10, 11, 12, 13, 14]
		},
		15
	]
}